odoo/addons/ssi_bill_of_service/README.rst
odoo/addons/ssi_bill_of_service/__init__.py
odoo/addons/ssi_bill_of_service/__manifest__.py
odoo/addons/ssi_bill_of_service/menu.xml
odoo/addons/ssi_bill_of_service/data/approval_template_data.xml
odoo/addons/ssi_bill_of_service/data/ir_sequence_data.xml
odoo/addons/ssi_bill_of_service/data/policy_template_data.xml
odoo/addons/ssi_bill_of_service/data/sequence_template_data.xml
odoo/addons/ssi_bill_of_service/models/__init__.py
odoo/addons/ssi_bill_of_service/models/bill_of_service.py
odoo/addons/ssi_bill_of_service/models/bill_of_service_pricelist.py
odoo/addons/ssi_bill_of_service/models/bill_of_service_type.py
odoo/addons/ssi_bill_of_service/models/product_product.py
odoo/addons/ssi_bill_of_service/security/ir.model.access.csv
odoo/addons/ssi_bill_of_service/security/ir_module_category_data.xml
odoo/addons/ssi_bill_of_service/security/ir_rule_data.xml
odoo/addons/ssi_bill_of_service/security/res_group_data.xml
odoo/addons/ssi_bill_of_service/static/description/icon.png
odoo/addons/ssi_bill_of_service/views/bill_of_service_pricelist_views.xml
odoo/addons/ssi_bill_of_service/views/bill_of_service_type_views.xml
odoo/addons/ssi_bill_of_service/views/bill_of_service_views.xml
odoo/addons/ssi_bill_of_service/views/product_product_views.xml
odoo14_addon_ssi_bill_of_service-14.0.3.0.2.dist-info/METADATA
odoo14_addon_ssi_bill_of_service-14.0.3.0.2.dist-info/WHEEL
odoo14_addon_ssi_bill_of_service-14.0.3.0.2.dist-info/top_level.txt
odoo14_addon_ssi_bill_of_service-14.0.3.0.2.dist-info/RECORD
